ayushbot/__init__.py
ayushbot/ayushbot.py
ayushbot/whatsapp.py
ayushbot-0.0.2.4.dist-info/LICENSE.txt
ayushbot-0.0.2.4.dist-info/METADATA
ayushbot-0.0.2.4.dist-info/WHEEL
ayushbot-0.0.2.4.dist-info/top_level.txt
ayushbot-0.0.2.4.dist-info/RECORD
